imio.pyutils-1.2.0-py3.13-nspkg.pth
imio/pyutils/__init__.py
imio/pyutils/batching.py
imio/pyutils/bs.py
imio/pyutils/postgres.py
imio/pyutils/system.py
imio/pyutils/tests.py
imio/pyutils/utils.py
imio_pyutils-1.2.0.dist-info/METADATA
imio_pyutils-1.2.0.dist-info/WHEEL
imio_pyutils-1.2.0.dist-info/namespace_packages.txt
imio_pyutils-1.2.0.dist-info/top_level.txt
imio_pyutils-1.2.0.dist-info/RECORD
