Metadata-Version: 2.4
Name: imio.pyutils
Version: 1.2.0
Summary: Some python useful methods
Home-page: https://github.com/imio/imio.pyutils/
Author: IMIO
Author-email: support@imio.be
License: GPL
Project-URL: PyPI, https://pypi.python.org/pypi/imio.pyutils
Project-URL: Source, https://github.com/imio/imio.pyutils
Keywords: Python IMIO
Classifier: Development Status :: 5 - Production/Stable
Classifier: License :: OSI Approved :: GNU General Public License (GPL)
Classifier: Operating System :: OS Independent
Classifier: Programming Language :: Python
Classifier: Programming Language :: Python :: 2.7
Classifier: Programming Language :: Python :: 3.10
Classifier: Programming Language :: Python :: 3.12
Classifier: Programming Language :: Python :: 3.13
Requires-Dist: setuptools
Requires-Dist: future
Requires-Dist: psutil
Requires-Dist: requests
Requires-Dist: shortuuid>=0.5.0
Requires-Dist: six>=1.16.0
Dynamic: author
Dynamic: author-email
Dynamic: classifier
Dynamic: description
Dynamic: home-page
Dynamic: keywords
Dynamic: license
Dynamic: project-url
Dynamic: requires-dist
Dynamic: summary
